ldt_identity_client/__init__.py
ldt_identity_client/api_client.py
ldt_identity_client/api_response.py
ldt_identity_client/configuration.py
ldt_identity_client/exceptions.py
ldt_identity_client/py.typed
ldt_identity_client/rest.py
ldt_identity_client/api/__init__.py
ldt_identity_client/api/invitations_api.py
ldt_identity_client/api/organizations_api.py
ldt_identity_client/api/service_accounts_api.py
ldt_identity_client/api/session_api.py
ldt_identity_client/api/user_roles_api.py
ldt_identity_client/api/users_api.py
ldt_identity_client/models/__init__.py
ldt_identity_client/models/add_org_user_request_inner.py
ldt_identity_client/models/create_service_account200_response.py
ldt_identity_client/models/create_service_account200_response_role.py
ldt_identity_client/models/create_service_account_request.py
ldt_identity_client/models/delete_org_users_request.py
ldt_identity_client/models/delete_service_account200_response.py
ldt_identity_client/models/get_service_accounts200_response_inner.py
ldt_identity_client/models/get_service_accounts200_response_inner_role.py
ldt_identity_client/models/initiate_password_reset_request.py
ldt_identity_client/models/invitation.py
ldt_identity_client/models/invitation_body.py
ldt_identity_client/models/org.py
ldt_identity_client/models/org_body.py
ldt_identity_client/models/post_session_google200_response.py
ldt_identity_client/models/post_session_google200_response_orgs_inner.py
ldt_identity_client/models/post_session_google200_response_services_inner.py
ldt_identity_client/models/post_session_google_request.py
ldt_identity_client/models/post_session_request.py
ldt_identity_client/models/regenerate_client_secret200_response.py
ldt_identity_client/models/service.py
ldt_identity_client/models/service_account.py
ldt_identity_client/models/update_invitation_request.py
ldt_identity_client/models/update_org_request.py
ldt_identity_client/models/update_org_user_request_inner.py
ldt_identity_client-1.0.2.dist-info/METADATA
ldt_identity_client-1.0.2.dist-info/WHEEL
ldt_identity_client-1.0.2.dist-info/top_level.txt
ldt_identity_client-1.0.2.dist-info/RECORD
